{"v":3,"stories":{"pages-categories--empty-list":{"id":"pages-categories--empty-list","title":"pages/categories","name":"Empty List","importPath":"./src/routes/categories.stories.tsx","tags":["story"],"kind":"pages/categories","story":"Empty List","parameters":{"__id":"pages-categories--empty-list","docsOnly":false,"fileName":"./src/routes/categories.stories.tsx"}},"pages-categories--default":{"id":"pages-categories--default","title":"pages/categories","name":"Default","importPath":"./src/routes/categories.stories.tsx","tags":["story"],"kind":"pages/categories","story":"Default","parameters":{"__id":"pages-categories--default","docsOnly":false,"fileName":"./src/routes/categories.stories.tsx"}},"pages-index--empty-list":{"id":"pages-index--empty-list","title":"pages/index","name":"Empty List","importPath":"./src/routes/index.stories.tsx","tags":["story"],"kind":"pages/index","story":"Empty List","parameters":{"__id":"pages-index--empty-list","docsOnly":false,"fileName":"./src/routes/index.stories.tsx"}},"pages-index--default":{"id":"pages-index--default","title":"pages/index","name":"Default","importPath":"./src/routes/index.stories.tsx","tags":["story"],"kind":"pages/index","story":"Default","parameters":{"__id":"pages-index--default","docsOnly":false,"fileName":"./src/routes/index.stories.tsx"}},"pages-index--multi-pages":{"id":"pages-index--multi-pages","title":"pages/index","name":"Multi Pages","importPath":"./src/routes/index.stories.tsx","tags":["story"],"kind":"pages/index","story":"Multi Pages","parameters":{"__id":"pages-index--multi-pages","docsOnly":false,"fileName":"./src/routes/index.stories.tsx"}},"pages-profile--default":{"id":"pages-profile--default","title":"pages/profile","name":"Default","importPath":"./src/routes/profile.stories.tsx","tags":["story"],"kind":"pages/profile","story":"Default","parameters":{"__id":"pages-profile--default","docsOnly":false,"fileName":"./src/routes/profile.stories.tsx"}}}}
